setup.py
rc4/__init__.py
rc4.egg-info/PKG-INFO
rc4.egg-info/SOURCES.txt
rc4.egg-info/dependency_links.txt
rc4.egg-info/top_level.txt